onealpha/__init__.py
onealpha/client.py
onealpha-0.1.3.dist-info/METADATA
onealpha-0.1.3.dist-info/WHEEL
onealpha-0.1.3.dist-info/top_level.txt
onealpha-0.1.3.dist-info/RECORD
