Metadata-Version: 2.4
Name: onealpha
Version: 0.1.3
Summary: TheOneAlpha Data Downloader: In this update, we enhanced the test.py file to ensure all endpoints are properly accessed and tested.
Author: Alok Vishwakarma
Author-email: alokvishwakarma@theonealpha.com
Classifier: Programming Language :: Python :: 3
Classifier: License :: OSI Approved :: MIT License
Classifier: Operating System :: OS Independent
Requires-Python: >=3.11
Dynamic: author
Dynamic: author-email
Dynamic: classifier
Dynamic: description
Dynamic: description-content-type
Dynamic: requires-python
Dynamic: summary
